{"frames":{"subBox.png":{"frame":{"x":0,"y":0,"w":443,"h":302,"idx":0},"spriteSourceSize":{"x":0,"y":0},"sourceSize":{"w":443,"h":302}},"tipsBox.png":{"frame":{"x":0,"y":304,"w":443,"h":252,"idx":0},"spriteSourceSize":{"x":0,"y":0},"sourceSize":{"w":443,"h":252}},"buyer1.png":{"frame":{"x":445,"y":0,"w":250,"h":288,"idx":0},"spriteSourceSize":{"x":0,"y":0},"sourceSize":{"w":250,"h":288}},"buyer2.png":{"frame":{"x":0,"y":558,"w":250,"h":288,"idx":0},"spriteSourceSize":{"x":0,"y":0},"sourceSize":{"w":250,"h":288}},"buyer3.png":{"frame":{"x":697,"y":0,"w":250,"h":288,"idx":0},"spriteSourceSize":{"x":0,"y":0},"sourceSize":{"w":250,"h":288}},"buyer4.png":{"frame":{"x":445,"y":290,"w":250,"h":288,"idx":0},"spriteSourceSize":{"x":0,"y":0},"sourceSize":{"w":250,"h":288}},"sgs.png":{"frame":{"x":0,"y":848,"w":248,"h":284,"idx":0},"spriteSourceSize":{"x":0,"y":0},"sourceSize":{"w":248,"h":284}},"ncts.png":{"frame":{"x":697,"y":290,"w":208,"h":244,"idx":0},"spriteSourceSize":{"x":0,"y":0},"sourceSize":{"w":208,"h":244}},"kehuQQ.png":{"frame":{"x":697,"y":536,"w":302,"h":125,"idx":0},"spriteSourceSize":{"x":0,"y":0},"sourceSize":{"w":302,"h":125}},"createRoleTitle.png":{"frame":{"x":252,"y":580,"w":377,"h":98,"idx":0},"spriteSourceSize":{"x":0,"y":0},"sourceSize":{"w":377,"h":98}},"tips1.png":{"frame":{"x":252,"y":680,"w":324,"h":104,"idx":0},"spriteSourceSize":{"x":0,"y":0},"sourceSize":{"w":324,"h":104}},"tips3.png":{"frame":{"x":252,"y":786,"w":324,"h":104,"idx":0},"spriteSourceSize":{"x":0,"y":0},"sourceSize":{"w":324,"h":104}},"tips2.png":{"frame":{"x":250,"y":892,"w":324,"h":104,"idx":0},"spriteSourceSize":{"x":0,"y":0},"sourceSize":{"w":324,"h":104}},"glodDot.png":{"frame":{"x":949,"y":0,"w":172,"h":179,"idx":0},"spriteSourceSize":{"x":0,"y":0},"sourceSize":{"w":172,"h":179}},"headerPicBg.png":{"frame":{"x":949,"y":181,"w":170,"h":179,"idx":0},"spriteSourceSize":{"x":0,"y":0},"sourceSize":{"w":170,"h":179}},"headerPicBgSel.png":{"frame":{"x":578,"y":680,"w":170,"h":179,"idx":0},"spriteSourceSize":{"x":0,"y":0},"sourceSize":{"w":170,"h":179}},"nxzhs.png":{"frame":{"x":250,"y":998,"w":335,"h":60,"idx":0},"spriteSourceSize":{"x":0,"y":0},"sourceSize":{"w":335,"h":60}},"k4.png":{"frame":{"x":250,"y":1060,"w":348,"h":57,"idx":0},"spriteSourceSize":{"x":0,"y":0},"sourceSize":{"w":348,"h":57}},"gwdg.png":{"frame":{"x":750,"y":663,"w":335,"h":59,"idx":0},"spriteSourceSize":{"x":0,"y":0},"sourceSize":{"w":335,"h":59}},"ndck.png":{"frame":{"x":750,"y":724,"w":335,"h":59,"idx":0},"spriteSourceSize":{"x":0,"y":0},"sourceSize":{"w":335,"h":59}},"ngw.png":{"frame":{"x":750,"y":785,"w":335,"h":59,"idx":0},"spriteSourceSize":{"x":0,"y":0},"sourceSize":{"w":335,"h":59}},"head_6.png":{"frame":{"x":907,"y":362,"w":135,"h":130,"idx":0},"spriteSourceSize":{"x":0,"y":0},"sourceSize":{"w":135,"h":130}},"head_3.png":{"frame":{"x":578,"y":861,"w":135,"h":130,"idx":0},"spriteSourceSize":{"x":0,"y":0},"sourceSize":{"w":135,"h":130}},"head_5.png":{"frame":{"x":600,"y":993,"w":135,"h":130,"idx":0},"spriteSourceSize":{"x":0,"y":0},"sourceSize":{"w":135,"h":130}},"head_4.png":{"frame":{"x":715,"y":861,"w":135,"h":130,"idx":0},"spriteSourceSize":{"x":0,"y":0},"sourceSize":{"w":135,"h":130}},"head_2.png":{"frame":{"x":852,"y":846,"w":135,"h":130,"idx":0},"spriteSourceSize":{"x":0,"y":0},"sourceSize":{"w":135,"h":130}},"head_1.png":{"frame":{"x":737,"y":993,"w":135,"h":130,"idx":0},"spriteSourceSize":{"x":0,"y":0},"sourceSize":{"w":135,"h":130}},"srk.png":{"frame":{"x":874,"y":978,"w":208,"h":49,"idx":0},"spriteSourceSize":{"x":0,"y":0},"sourceSize":{"w":208,"h":49}},"getVerCode.png":{"frame":{"x":874,"y":1029,"w":210,"h":47,"idx":0},"spriteSourceSize":{"x":0,"y":0},"sourceSize":{"w":210,"h":47}},"yzmk.png":{"frame":{"x":874,"y":1078,"w":123,"h":47,"idx":0},"spriteSourceSize":{"x":0,"y":0},"sourceSize":{"w":123,"h":47}},"submit.png":{"frame":{"x":907,"y":494,"w":120,"h":40,"idx":0},"spriteSourceSize":{"x":0,"y":0},"sourceSize":{"w":120,"h":40}},"cancel.png":{"frame":{"x":989,"y":846,"w":120,"h":40,"idx":0},"spriteSourceSize":{"x":0,"y":0},"sourceSize":{"w":120,"h":40}},"confirm.png":{"frame":{"x":989,"y":888,"w":120,"h":40,"idx":0},"spriteSourceSize":{"x":0,"y":0},"sourceSize":{"w":120,"h":40}},"inputBg.png":{"frame":{"x":1044,"y":362,"w":75,"h":62,"idx":0},"spriteSourceSize":{"x":0,"y":0},"sourceSize":{"w":75,"h":62}},"clearBtn.png":{"frame":{"x":1044,"y":426,"w":65,"h":66,"idx":0},"spriteSourceSize":{"x":0,"y":0},"sourceSize":{"w":65,"h":66}},"kehu.png":{"frame":{"x":631,"y":580,"w":48,"h":48,"idx":0},"spriteSourceSize":{"x":0,"y":0},"sourceSize":{"w":48,"h":48}},"play_music.png":{"frame":{"x":907,"y":290,"w":39,"h":39,"idx":0},"spriteSourceSize":{"x":0,"y":0},"sourceSize":{"w":39,"h":39}},"stop_music.png":{"frame":{"x":999,"y":1078,"w":39,"h":39,"idx":0},"spriteSourceSize":{"x":0,"y":0},"sourceSize":{"w":39,"h":39}},"vercode.png":{"frame":{"x":1029,"y":494,"w":67,"h":21,"idx":0},"spriteSourceSize":{"x":0,"y":0},"sourceSize":{"w":67,"h":21}},"changeBind.png":{"frame":{"x":989,"y":930,"w":56,"h":22,"idx":0},"spriteSourceSize":{"x":0,"y":0},"sourceSize":{"w":56,"h":22}},"add.png":{"frame":{"x":907,"y":331,"w":30,"h":29,"idx":0},"spriteSourceSize":{"x":0,"y":0},"sourceSize":{"w":30,"h":29}},"max.png":{"frame":{"x":250,"y":1119,"w":41,"h":15,"idx":0},"spriteSourceSize":{"x":0,"y":0},"sourceSize":{"w":41,"h":15}},"null.png":{"frame":{"x":1123,"y":0,"w":20,"h":28,"idx":0},"spriteSourceSize":{"x":0,"y":0},"sourceSize":{"w":20,"h":28}},"reduce.png":{"frame":{"x":252,"y":558,"w":29,"h":11,"idx":0},"spriteSourceSize":{"x":0,"y":0},"sourceSize":{"w":29,"h":11}}},"meta":{"app":"http:\/\/www.layabox.com","version":"1.00","format":"json","scale":1,"image":"createRole.png","prefix":"createRole\/","md5":"319c4105e3f512bbd2f8fd2a1d5c624a"}}
